Workbook
Name aA: SIMULADOR!$S$13

Sheet SIMULADOR
B14: Configurações
B15: Salário | E15: 2600
B16: Rendimento Carteira | E16: 0.01
B17: Sugestão de investimento | E17: 0.1
B20: Investimento Mensal
B21: Quanto invertir por mês ? | E21: =E15*E17 -> 260
B22: Por quantos anos investir ? | E22: 5
B23: Taxa de rendimento mensal | E23: 0.0109
B24: Taxa de rendimento anual | E24: =(1+E23)^12-1 -> 0.13893348
B25: Patrimonio acumulado ? | E25: =FV(E23,12*E22,-E21) -> 21859.675
B26: Dividendos mensais ? | E26: =E25*E23 -> 238.27046
B28: Cenários | F28: Dividendo
B29: Quanto em anos? | D29: 2 | E29: =FV($E$23,D29*12,-$E$21) -> 7088.446 | F29: =E29*$E$16 -> 70.88446
B30: Quanto em anos? | D30: 5 | E30: =FV($E$23,D30*12,-$E$21) -> 21859.675 | F30: =E30*$E$16 -> 218.59675
B31: Quanto em anos? | D31: 10 | E31: =FV($E$23,D31*12,-$E$21) -> 63752.1 | F31: =E31*$E$16 -> 637.521
B32: Quanto em anos? | D32: 20 | E32: =FV($E$23,D32*12,-$E$21) -> 297893.43 | F32: =E32*$E$16 -> 2978.9343
B33: Quanto em anos? | D33: 30 | E33: =FV($E$23,D33*12,-$E$21) -> 1157820.6 | F33: =E33*$E$16 -> 11578.206
B38: Pefil | F38: CONSERVADOR
B39: Valor a ser investido por mês: | F39: =E21 -> 260
B42: TIPOS DE FFI | E42: Percentual Sugerido | F42: Valores
B43: PAPEL | E43: =VLOOKUP($F$38&"-"&B43,BASE!B2:E20,4,0) -> 0.3 | F43: =E43*$F$39 -> 78
B44: TIJOLO | E44: =VLOOKUP($F$38&"-"&B44,BASE!B3:E21,4,0) -> 0.5 | F44: =E44*$F$39 -> 130
B45: HÍBRIDOS | E45: =VLOOKUP($F$38&"-"&B45,BASE!B4:E22,4,0) -> 0.1 | F45: =E45*$F$39 -> 26
B46: FOFs | E46: =VLOOKUP($F$38&"-"&B46,BASE!B5:E23,4,0) -> 0.1 | F46: =E46*$F$39 -> 26
B47: DESENVOLVIMENTO | E47: =VLOOKUP($F$38&"-"&B47,BASE!B6:E24,4,0) -> 0 | F47: =E47*$F$39 -> 0
B48: HOTELARIAS | E48: =VLOOKUP($F$38&"-"&B48,BASE!B7:E25,4,0) -> 0 | F48: =E48*$F$39 -> 0

Sheet BASE
B2: CHAVE | C2: PERFIL | D2: TIPO DE FII | E2: %
B3: =C3&"-"&D3 -> CONSERVADOR-PAPEL | C3: CONSERVADOR | D3: PAPEL | E3: 0.3
B4: =C4&"-"&D4 -> CONSERVADOR-TIJOLO | C4: CONSERVADOR | D4: TIJOLO | E4: 0.5
B5: =C5&"-"&D5 -> CONSERVADOR-HÍBRIDOS | C5: CONSERVADOR | D5: HÍBRIDOS | E5: 0.1
B6: =C6&"-"&D6 -> CONSERVADOR-FOFs | C6: CONSERVADOR | D6: FOFs | E6: 0.1
B7: =C7&"-"&D7 -> CONSERVADOR-DESENVOLVIMENTO | C7: CONSERVADOR | D7: DESENVOLVIMENTO | E7: 0
B8: =C8&"-"&D8 -> CONSERVADOR-HOTELARIAS | C8: CONSERVADOR | D8: HOTELARIAS | E8: 0
B9: =C9&"-"&D9 -> MODERADO-PAPEL | C9: MODERADO | D9: PAPEL | E9: 0.32
B10: =C10&"-"&D10 -> MODERADO-TIJOLO | C10: MODERADO | D10: TIJOLO | E10: 0.35
B11: =C11&"-"&D11 -> MODERADO-HÍBRIDOS | C11: MODERADO | D11: HÍBRIDOS | E11: 0.08
B12: =C12&"-"&D12 -> MODERADO-FOFs | C12: MODERADO | D12: FOFs | E12: 0.05
B13: =C13&"-"&D13 -> MODERADO-DESENVOLVIMENTO | C13: MODERADO | D13: DESENVOLVIMENTO | E13: 0.1
B14: =C14&"-"&D14 -> MODERADO-HOTELARIAS | C14: MODERADO | D14: HOTELARIAS | E14: 0.1
... B20: =C20&"-"&D20 -> AGRESSIVO-HOTELARIAS | C20: AGRESSIVO | D20: HOTELARIAS | E20: 0.1
